tinyconf/__init__.py
tinyconf/deserializers.py
tinyconf/fields.py
tinyconf/section.py
tinyconf-0.3.0.dist-info/LICENSE
tinyconf-0.3.0.dist-info/METADATA
tinyconf-0.3.0.dist-info/WHEEL
tinyconf-0.3.0.dist-info/top_level.txt
tinyconf-0.3.0.dist-info/RECORD
