Metadata-Version: 2.1
Name: tinyconf
Version: 0.3.0
Summary: A declarative config parsing library
Home-page: https://github.com/jellywx/tinyconf
Author: JellyWX
Author-email: judewrs@gmail.com
License: UNKNOWN
Platform: UNKNOWN
Classifier: Development Status :: 3 - Alpha
Classifier: Programming Language :: Python :: 3.5
Classifier: Programming Language :: Python :: 3.6
Classifier: Natural Language :: English
Classifier: Intended Audience :: Developers
Classifier: License :: OSI Approved :: MIT License
Classifier: Operating System :: OS Independent
Classifier: Topic :: Utilities
